[{"modelo":"X200","empresa":"amazon-robotics","metrica":"net_upload","data":"2022-03-01","mediaGeral":0.002533354166666667,"mediaPico":0.0,"uptimeTotal":2340.0,"uptimePico":0.0,"acima95":0},{"modelo":"X200","empresa":"amazon-robotics","metrica":"cpu_freq","data":"2022-03-01","mediaGeral":3.7018435624999992,"mediaPico":0.0,"uptimeTotal":2340.0,"uptimePico":0.0,"acima95":0},{"modelo":"X200","empresa":"amazon-robotics","metrica":"disk_percent","data":"2022-03-01","mediaGeral":57.25661025,"mediaPico":0.0,"uptimeTotal":2340.0,"uptimePico":0.0,"acima95":0},{"modelo":"X200","empresa":"amazon-robotics","metrica":"net_usage","data":"2022-03-01","mediaGeral":85.91335468750002,"mediaPico":117.61669513793106,"uptimeTotal":2340.0,"uptimePico":1368.0,"acima95":19},{"modelo":"X200","empresa":"amazon-robotics","metrica":"battery_percent","data":"2022-03-01","mediaGeral":28.920460416666668,"mediaPico":0.0,"uptimeTotal":2340.0,"uptimePico":0.0,"acima95":0},{"modelo":"X200","empresa":"amazon-robotics","metrica":"cpu_percent","data":"2022-03-01","mediaGeral":43.89707591666667,"mediaPico":98.34945144444445,"uptimeTotal":2340.0,"uptimePico":449.0,"acima95":6},{"modelo":"X200","empresa":"amazon-robotics","metrica":"disk_usage_gb","data":"2022-03-01","mediaGeral":45.92056458333334,"mediaPico":0.0,"uptimeTotal":2340.0,"uptimePico":0.0,"acima95":0},{"modelo":"X200","empresa":"amazon-robotics","metrica":"ram_percent","data":"2022-03-01","mediaGeral":41.96575135416666,"mediaPico":76.93430366666666,"uptimeTotal":2340.0,"uptimePico":161.5,"acima95":0},{"modelo":"X200","empresa":"amazon-robotics","metrica":"ram_usage_gb","data":"2022-03-01","mediaGeral":5.220189500000001,"mediaPico":0.0,"uptimeTotal":2340.0,"uptimePico":0.0,"acima95":0},{"modelo":"X200","empresa":"amazon-robotics","metrica":"net_download","data":"2022-03-01","mediaGeral":0.02441887500000001,"mediaPico":0.0,"uptimeTotal":2340.0,"uptimePico":0.0,"acima95":0}]